{
  "project": "Test Pipeline",
  "status": "running",
  "startTime": "2026-01-28T07:07:23Z",
  "agents": {
    "atlas": {
      "status": "idle",
      "location": "lounge",
      "tokens": 15000,
      "task": null
    },
    "nova": {
      "status": "idle",
      "location": "lounge",
      "tokens": 45000,
      "task": null
    },
    "sage": {
      "status": "idle",
      "location": "lounge",
      "tokens": 12000,
      "task": null
    },
    "phoenix": {
      "status": "idle",
      "location": "lounge",
      "tokens": 20000,
      "task": null
    },
    "shadow": {
      "status": "idle",
      "location": "bar",
      "tokens": 18000,
      "task": null
    },
    "echo": {
      "status": "active",
      "location": "table4",
      "tokens": 0,
      "task": "Generating test cases..."
    },
    "bolt": {
      "status": "active",
      "location": "table4",
      "tokens": 0,
      "task": "Preparing test runner..."
    },
    "scribe": {
      "status": "active",
      "location": "table4",
      "tokens": 0,
      "task": "Drafting documentation..."
    }
  },
  "logs": [
    {
      "agent": null,
      "message": "Pipeline started for Test Pipeline"
    },
    {
      "agent": "Atlas",
      "message": "moved to Table 1 (PLAN)"
    },
    {
      "agent": "Atlas",
      "message": "completed planning, moving to lounge"
    },
    {
      "agent": "Nova",
      "message": "moved to Table 2 (BUILD)"
    },
    {
      "agent": "Phoenix",
      "message": "moved to Table 2 (BUILD)"
    },
    {
      "agent": "Sage",
      "message": "moved to Table 3 (GUARD)"
    },
    {
      "agent": "Shadow",
      "message": "moved to Table 3 (GUARD)"
    },
    {
      "agent": "Echo",
      "message": "moved to Table 4 (VERIFY)"
    },
    {
      "agent": "Bolt",
      "message": "moved to Table 4 (VERIFY)"
    }
  ],
  "console": [
    {
      "text": "Pipeline initialized: Test Pipeline",
      "type": "success"
    },
    {
      "text": "Stage 1: Planning started",
      "type": "warning"
    },
    {
      "text": "Atlas: Requirements analyzed ✓",
      "type": "success"
    },
    {
      "text": "Stage 2: Building started",
      "type": "warning"
    },
    {
      "text": "Nova: Core implementation complete ✓",
      "type": "success"
    },
    {
      "text": "Phoenix: Code polished ✓",
      "type": "success"
    },
    {
      "text": "Stage 3: Quality Guard started",
      "type": "warning"
    },
    {
      "text": "Sage: Code quality verified ✓",
      "type": "success"
    },
    {
      "text": "Shadow: No vulnerabilities found ✓",
      "type": "success"
    }
  ],
  "stats": {
    "totalTokens": 90000,
    "totalCost": 0.90,
    "tasksComplete": 4,
    "totalTasks": 8
  }
}
